odoo9_addon_mgmtsystem_kpi-9.0.1.0.0.99.dev15-py3.8-nspkg.pth
odoo_addons/mgmtsystem_kpi/README.rst
odoo_addons/mgmtsystem_kpi/__init__.py
odoo_addons/mgmtsystem_kpi/__openerp__.py
odoo_addons/mgmtsystem_kpi/i18n/es.po
odoo_addons/mgmtsystem_kpi/i18n/fr.po
odoo_addons/mgmtsystem_kpi/i18n/mgmtsystem_kpi.pot
odoo_addons/mgmtsystem_kpi/i18n/nb.po
odoo_addons/mgmtsystem_kpi/i18n/pt_BR.po
odoo_addons/mgmtsystem_kpi/static/description/icon.png
odoo_addons/mgmtsystem_kpi/views/menu.xml
odoo9_addon_mgmtsystem_kpi-9.0.1.0.0.99.dev15.dist-info/METADATA
odoo9_addon_mgmtsystem_kpi-9.0.1.0.0.99.dev15.dist-info/WHEEL
odoo9_addon_mgmtsystem_kpi-9.0.1.0.0.99.dev15.dist-info/namespace_packages.txt
odoo9_addon_mgmtsystem_kpi-9.0.1.0.0.99.dev15.dist-info/top_level.txt
odoo9_addon_mgmtsystem_kpi-9.0.1.0.0.99.dev15.dist-info/RECORD
